Workbook

Sheet Company description
A1: Item | B1: Detail
A2: Company name: | B2: Example E-Shop Ltd.
A3: Industry: | B3: E-commerce / Online retail
A4: Location: | B4: EU-focused, based in Poland (fictional)
A5: Business model: | B5: Marketplace and direct retail; subscription-driven loyalty program
A6: Key points: | B6: High gross margins on private-label items, seasonal sales peaks, growth via marketing & international expansion
A7: Investment thesis: | B7: Scalable unit economics, strong customer retention, opportunity to improve working capital and expand gross margin through private label

Sheet P&L
A1: $USK | B1: FY24 | C1: FY25 | D1: FY26B | G1: Key:
A2: Revenue (Net Sales): | B2: 664389 | C2: 653378 | D2: =C2*'[1]Development Factoring P&L'!G4 -> 664214.95 | G2: FY23: | H2: 31/01/2022-31/01/2023
A3: COGS | B3: 300230 | C3: 300238 | D3: =C3*'[1]Development Factoring P&L'!G5 -> 303913.86 | G3: FY24: | H3: 31/01/2023-31/01/2024
A4: Gross Profit | B4: 364159 | C4: 353140 | D4: =C4*'[1]Development Factoring P&L'!G6 -> 360303.92 | G4: FY25 | H4: 31/01/2024-31/01/2025
A5: SG&A (opex) | B5: 315689 | C5: 333125 | D5: =C5*'[1]Development Factoring P&L'!G7 -> 333041.72
A6: Depreciation & Amortization | B6: 9644 | C6: 9312 | D6: =C6*'[1]DF Cash Flows'!E21 -> 9417.6966
A7: EBIT | B7: 48470 | C7: 20015 | D7: =C7*'[1]Development Factoring P&L'!G8 -> 29713.735
A8: Interest expense | B8: 497 | C8: 489 | D8: =C8*'[1]Development Factoring P&L'!G11 -> 469.28226
A9: Pre-tax income | B9: 53967 | C9: 26651 | D9: =C9*'[1]Development Factoring P&L'!G12 -> 33288.752
A10: Tax (21%) | B10: =B9*0.21 -> 11333.07 | C10: =C9*0.21 -> 5596.71 | D10: =D9*0.21 -> 6990.638 | E10: Assumed to be flate-rate, this is why it there is mismatch
A11: Net income | B11: 41345 | C11: 18364 | D11: =C11*'[1]Development Factoring P&L'!G18 -> 24914.557
A13: One-off and non recuring items proposed by the Sellers:
A14: Personal costs included in the P&L | B14: 0 | C14: 0 | D14: 0
A15: Founder's salary (he stays post transaction) | E15: N/A
A16: One-off costs | B16: 0 | C16: 0 | D16: 0
A17: Income from subsidies | B17: 0 | C17: 0 | D17: 0
A19: Adjusted EBITDA calculation:
A20: Reported EBITDA | B20: =B7+B6 -> 58114 | C20: =C7+C6 -> 29327 | D20: =D7+D6 -> 39131.432
A21: Adjustments:
A22: =A14 -> Personal costs included in the P&L
A23: =A16 -> One-off costs | B23: =B16 -> 0 | C23: 0 | D23: 0
A24: =A17 -> Income from subsidies | B24: =-B17 -> 0 | C24: =-C17 -> 0 | D24: =-D17 -> 0
A25: Adjusted EBITDA | B25: =SUM(B20:B24) -> 58114 | C25: =SUM(C20:C24) -> 29327 | D25: =SUM(D20:D24) -> 39131.432

Sheet Balance sheet
A1: Assets | B1: FY24 | C1: FY25 | D1: FY26B
A2: Cash and equivalents | B2: 262059 | C2: 208501 | D2: =C2*'[1]DF Balance Sheet'!E6 -> 211174.62
A3: Accounts receivable | B3: 86044 | C3: 93382 | D3: =C3*'[1]DF Balance Sheet'!E7 -> 97038.443
A4: Inventory | B4: 153890 | C4: 156738 | D4: =C4*'[1]DF Balance Sheet'!E8 -> 175224.04
A5: Other current assets | B5: 17962 | C5: 21786 | D5: =C5*'[1]DF Balance Sheet'!E9 -> 18233.799
A6: Total current assets | B6: 531294 | C6: 489941 | D6: =C6*'[1]DF Balance Sheet'!E11 -> 510020.78
A7: PP&E (net) | B7: 19436 | C7: 19920 | D7: =C7*'[1]DF Balance Sheet'!E12 -> 17716.934
A8: Intangibles (goodwill) | B8: =82661+7493 -> 90154 | C8: =86009+5537 -> 91546 | D8: =C8*'[1]DF Balance Sheet'!G11 -> 74107.933
A9: Total non-current assets | B9: =SUM(B7:B8) -> 109590 | C9: =SUM(C7:C8) -> 111466 | D9: =SUM(D7:D8) -> 91824.867
A10: Total assets | B10: 756498 | C10: 729231 | D10: =C10*'[1]DF Balance Sheet'!E17 -> 733864.14
A11: Accounts payable | B11: 32775 | C11: 34312 | D11: =C11*'[1]DF Balance Sheet'!E20 -> 31653.692
A12: Accrued expenses | B12: 38695 | C12: 42610 | D12: =C12*'[1]DF Balance Sheet'!E21 -> 54131.028
A13: Short-term bank debt | B13: 0 | C13: 0 | D13: 0
A14: Long-term bank debt | B14: 0 | C14: 0 | D14: 0
A15: Other long-term liabilities | B15: 0 | C15: 0 | D15: 0
A16: Total liabilities | B16: 248449 | C16: 245652 | D16: =C16*'[1]DF Balance Sheet'!E29 -> 244399.02
A17: Shareholders' equity | B17: 505890 | C17: 481329 | D17: =C17*'[1]DF Balance Sheet'!E50 -> 487214.89
A18: Total liabilities & equity | B18: 756498 | C18: 729321 | D18: =C18*'[1]DF Balance Sheet'!E51 -> 733954.71
A20: Potential Net Debt Items:
A21: Overdue liabilities (0-90 days) | B21: 0 | C21: 0 | D21: 0
A22: Overdue liabilities (>90 days) | B22: 0 | C22: 0 | D22: 0
A23: Unpaid dividends | B23: 0 | C23: 0 | D23: 0
A25: Net Debt calculation:
A26: Short-term bank debt | B26: =B13 -> 0 | C26: =C13 -> 0 | D26: =D13 -> 0 | E26: Zero-Debt Company
A27: Long-term bank debt | B27: 0 | C27: 0 | D27: 0
A28: Other long-term liabilities | B28: =B15 -> 0 | C28: =C15 -> 0 | D28: =D15 -> 0
A29: =A2 -> Cash and equivalents | B29: =-B2 -> -262059 | C29: =-C2 -> -208501 | D29: =-D2 -> -211174.62
A30: Reported Net Debt | B30: =SUM(B26:B29) -> -262059 | C30: =SUM(C26:C29) -> -208501 | D30: =SUM(D26:D29) -> -211174.62
A31: =A22 -> Overdue liabilities (>90 days) | B31: 0 | C31: 0 | D31: 0
A32: =A23 -> Unpaid dividends | B32: 0 | C32: 0 | D32: 0
A33: Adjusted Net Debt | B33: =B30+B31+B32 -> -262059 | C33: =C30+C31+C32 -> -208501 | D33: =D30+D31+D32 -> -211174.62
A35: Part of the debt for refinancing | B35: =B26+B27 -> 0 | C35: =C26+C27 -> 0 | D35: =D26+D27 -> 0
A36: Part of the debt for roll-over | B36: =B33-B35 -> -262059 | C36: =C33-C35 -> -208501 | D36: =D33-D35 -> -211174.62

Sheet Cash flows
B1: FY24 | C1: FY25 | D1: FY26B
A2: Net income | B2: 42175 | C2: 19209 | D2: =C2*'[1]DF Cash Flows'!E18 -> 25155.196
A3: Depreciation & amortization | B3: 9644 | C3: 9312 | D3: 9312
A4: Change in working capital | B4: {=SUM('[1]DF Cash Flows'!C84:C86-'[1]DF Cash Flows'!C87:C89)} -> 55130 | C4: {=SUM('[1]DF Cash Flows'!B84:B86-'[1]DF Cash Flows'!B87:B89)} -> -33283 | D4: =C4*'[1]DF Cash Flows'!G52 -> -25908.66
A5: Other adjustments | B5: 0 | C5: 0 | D5: 0
A6: Cash flow from operations (CFO) | B6: 76778 | C6: -1504 | D6: =C6*'[1]DF Cash Flows'!E38 -> 46.86696
A7: Capital expenditures (CapEx) | B7: -8223 | C7: -7966 | D7: =C7*'[1]DF Cash Flows'!E40 -> -4393.309
A8: Acquisitions (cash) | B8: -114 | C8: -109 | D8: =C8*'[1]DF Cash Flows'!E42 -> -73.511628
A9: Cash flow from investing (CFI) | B9: -11474 | C9: -13742 | D9: =C9*'[1]DF Cash Flows'!E43 -> -7258.9023
A10: Debt issued (net) | B10: 0 | C10: 0 | D10: 0
A11: Equity issued / repurchased | B11: -3116 | C11: =-(1101+2628) -> -3729 | D11: =C11*'[1]DF Cash Flows'!F47 -> -2068
A12: Dividends paid | B12: -53146 | C12: -31069 | D12: =C12*'[1]DF Cash Flows'!F45 -> -31051.679
A13: Cash flow from financing (CFF) | B13: -57596 | C13: -35402 | D13: =C13*'[1]DF Cash Flows'!E48 -> -33210.971
A14: Net change in cash | B14: =B6+B13+B9 -> 7708 | C14: =C6+C13+C9 -> -50648 | D14: =D6+D13+D9 -> -40423.006

Sheet Transaction assumptions
B1: Value
A2: Deal type | B2: LBO - Majority buyout
A3: Sponsor ownership post-close (%) | B3: 0.7
A4: Purchase date | B4: 46022
A5: Fees & transaction costs (PLN thousands) | B5: ='Calculations & S&U'!B5*0.02 -> 5865.4

Sheet Historical EV_EBITDA (deals)
A1: Deal | B1: Year | C1: EV/EBITDA | D1: Target's HQ
A2: Acquirer A / Target X | B2: 2023 | C2: 6.2 | D2: Poland
A3: Acquirer B / Target Y | B3: 2022 | C3: 8.1 | D3: Germany
A4: Acquirer C / Target Z | B4: 2015 | C4: 7 | D4: USA
A5: Acquirer D / Target Q | B5: 2024 | C5: 9 | D5: Argentina
A6: Acquirer E / Target R | B6: 2020 | C6: 5.5 | D6: France
A8: Deals used for analysis:
A9: Deal | B9: Year | C9: EV/EBITDA | D9: Target's HQ
A10: Acquirer A / Target X | B10: 2023 | C10: 6.2 | D10: Poland
A11: Acquirer B / Target Y | B11: 2022 | C11: 8.1 | D11: Germany
A12: Acquirer E / Target R | B12: 2020 | C12: 5.5 | D12: France
A14: Average | C14: =AVERAGE(C10:C12) -> 6.6

Sheet Public EV_EBITDA (public)
A1: Ticker | B1: Company | C1: Market Cap ($USk) | D1: Enterprise Value ($USk) | E1: EBITDA ($USk) | F1: EV/EBITDA | G1: HQ
A2: SWGAY | B2: Swatch | C2: 11070000 | D2: 9720000 | E2: 546000 | F2: 12.66 | G2: Switzerland
A3: FOSL | B3: Fossil | C3: 231188 | D3: 472690 | E3: 44100 | F3: =D3/E3 -> 10.718594 | G3: USA
A4: 8050.T | B4: Seiko | C4: 48000000 | D4: 2370000 | E4: 250000 | F4: 9.1 | G4: Japan
A5: ECOM4 | B5: Richemont | C5: 148000000 | D5: 144000000 | E5: 5350000 | F5: 15.11 | G5: Switzerland
A7: Average | F7: =AVERAGE(F2:F5) -> 11.897149

Sheet Calculations & S&U
A2: Enterprise Value calculation:
A3: Adj. EBITDA | B3: ='P&L'!C25 -> 29327 | C3: 2025 | E3: Stock Price (31/12/2025: | F3: Shares Outstanding: | G3: Net Debt:
A4: EV/EBITDA Multiple | B4: 10 | C4: average | E4: 19.12 | F4: =(6458376+6483116)/1000 -> 12941.492 | G4: ='Balance sheet'!C33 -> -208501
A5: Enterprise Value | B5: =B3*B4 -> 293270
A7: Net debt calculation:
A8: Net debt prior to transaction | B8: ='Balance sheet'!C33 -> -208501
A9: incl: refinanced debt | B9: ='Balance sheet'!C35 -> 0
A10: incl: rolled-over debt | B10: ='Balance sheet'!C36 -> -208501
A12: New debt | B12: =4*B3 -> 117308 | C12: 3x EBITDA
A13: Net debt post transaction | B13: =B12+B10 -> -91193
A14: Net debt / Adj. EBITDA | B14: =B13/B3 -> -3.1095236
A16: Equity Value calculation:
A17: Enterprise Value | B17: =B5 -> 293270
A18: Net debt post transaction | B18: =B13 -> -91193
A19: 100% Equity Value | B19: =B17-B18 -> 384463
A20: Stake acquired by the Fund | B20: ='Transaction assumptions'!B3 -> 0.7
A21: Fund's Equity Value | B21: =B19*B20 -> 269124.1
A22: Founder's Equity Value | B22: =B19-B21 -> 115338.9
A23: Transaction costs | B23: ='Transaction assumptions'!B5 -> 5865.4
A24: Fund's Equity Ticket | B24: =B21+B23 -> 274989.5
A26: Sources:
A27: Fund's equity | B27: =B24 -> 274989.5
A28: Founder's equity (rollover) | B28: =B22 -> 115338.9
A29: Existing debt (rollover) | B29: =B10 -> -208501
A30: New debt | B30: =B12 -> 117308
A31: Total sources: | B31: =SUM(B27:B30) -> 299135.4
A33: Uses:
A34: Founder's cash-out (from equity) | B34: =B21 -> 269124.1
A35: Founder's cash-out (from debt) | B35: =B12-B9 -> 117308
A36: Founder's equity (rollover) | B36: =B22 -> 115338.9
A37: Transaction costs | B37: =B23 -> 5865.4
A38: Roll-over of current debt | B38: =B10 -> -208501
A39: Debt refinancing | B39: =B9 -> 0
A40: Total uses: | B40: =SUM(B34:B39) -> 299135.4

Sheet P&L forecast
A1: Income Statement Forecast (thousand $US)
A3: Income Statement
A4: Item | B4: FY24 | C4: FY25 | D4: FY26B | E4: FY27 | F4: FY28 | G4: FY29 | H4: FY30
A5: Revenue | B5: ='P&L'!B2 -> 664389 | C5: ='P&L'!C2 -> 653378 | D5: ='P&L'!D2 -> 664214.95 | E5: =D5*(1+E6) -> 677499.25 | F5: =E5*(1+F6) -> 704599.22 | G5: =F5*(1+G6) -> 739829.18 | H5: =G5*(1+H6) -> 791617.22
A6: Revenue growth | C6: =C5/B5-1 -> -0.016573122 | D6: =D5/C5-1 -> 0.016586036 | E6: 0.02 | F6: 0.04 | G6: 0.05 | H6: 0.07
A8: COGS | B8: =B9-B5 -> -300230 | C8: =C9-C5 -> -300238 | D8: =D9-D5 -> -303911.03 | E8: =E9-E5 -> -309989.25 | F8: =F9-F5 -> -315342.83 | G8: =G9-G5 -> -323711.68 | H8: =H9-H5 -> -338455.33
A9: Gross Profit | B9: ='P&L'!B4 -> 364159 | C9: ='P&L'!C4 -> 353140 | D9: ='P&L'!D4 -> 360303.92 | E9: =E10*E5 -> 367510 | F9: =F10*F5 -> 389256.39 | G9: =G10*G5 -> 416117.5 | H9: =H10*H5 -> 453161.9
A10: Gross Profit (%) | B10: =B9/B5 -> 0.54811112 | C10: =C9/C5 -> 0.54048346 | D10: =D9/D5 -> 0.54245078 | E10: =D10 -> 0.54245078 | F10: =E10+1% -> 0.55245078 | G10: =F10+1% -> 0.56245078 | H10: =G10+1% -> 0.57245078
A12: Opex | B12: =-'P&L'!B5 -> -315689 | C12: =-'P&L'!C5 -> -333125 | D12: =-'P&L'!D5 -> -333041.72 | E12: =D12*(1+E13) -> -342197.3 | F12: =E12*(1+F13) -> -351604.58 | G12: =F12*(1+G13) -> -361270.46 | H12: =G12*(1+H13) -> -371202.08
A13: Opex (y/y) | C13: =C12/B12-1 -> 0.055231573 | D13: =D12/C12-1 -> -0.00024999078 | E13: =AVERAGE(C13:D13) -> 0.027490791 | F13: =E13 -> 0.027490791 | G13: =F13 -> 0.027490791 | H13: =G13 -> 0.027490791
A14: Additional Management cost | D14: -3000 | E14: =D14*1.1 -> -3300 | F14: =E14*1.1 -> -3630 | G14: =F14*1.1 -> -3993 | H14: =G14*1.1 -> -4392.3
A15: EBITDA | B15: ='P&L'!B20 -> 58114 | C15: ='P&L'!C20 -> 29327 | D15: ='P&L'!D20 -> 39131.432 | E15: =D15*1.03 -> 40305.375 | F15: =E15*1.09 -> 43932.859 | G15: =F15*1.1 -> 48326.144 | H15: =G15*1.12 -> 54125.282
A16: EBITDA (%) | B16: =B15/B5 -> 0.087469841 | C16: =C15/C5 -> 0.044885197 | D16: =D15/D5 -> 0.058913808 | E16: =E15/E5 -> 0.059491394 | F16: =F15/F5 -> 0.062351557 | G16: =G15/G5 -> 0.065320679 | H16: =H15/H5 -> 0.068373047
A18: Adjustments | B18: ='P&L'!B22+'P&L'!B23+'P&L'!B24 -> 0 | C18: ='P&L'!C22+'P&L'!C23+'P&L'!C24 -> 0 | D18: ='P&L'!D22+'P&L'!D23+'P&L'!D24 -> 0 | E18: 0 | F18: 0 | G18: 0 | H18: 0
A19: Adj. EBITDA | B19: =B15+B18 -> 58114 | C19: =C15+C18 -> 29327 | D19: =D15+D18 -> 39131.432 | E19: =E15+E18 -> 40305.375 | F19: =F15+F18 -> 43932.859 | G19: =G15+G18 -> 48326.144 | H19: =H15+H18 -> 54125.282
A20: Adj. EBITDA (%) | B20: =B19/B5 -> 0.087469841 | C20: =C19/C5 -> 0.044885197 | D20: =D19/D5 -> 0.058913808 | E20: =E19/E5 -> 0.059491394 | F20: =F19/F5 -> 0.062351557 | G20: =G19/G5 -> 0.065320679 | H20: =H19/H5 -> 0.068373047
A22: Depreciation | B22: =-'P&L'!B6 -> -9644 | C22: =-'P&L'!C6 -> -9312 | D22: =-'P&L'!D6 -> -9417.6966 | E22: =D22-300 -> -9717.6966 | F22: =E22-300 -> -10017.697 | G22: =F22-300 -> -10317.697 | H22: =G22-300 -> -10617.697
A23: EBIT | B23: =B15+B22 -> 48470 | C23: =C15+C22 -> 20015 | D23: =D15+D22 -> 29713.735 | E23: =E15+E22 -> 30587.678 | F23: =F15+F22 -> 33915.162 | G23: =G15+G22 -> 38008.448 | H23: =H15+H22 -> 43507.585
A25: Interest expense (tax deductible) | B25: =-'P&L'!B8 -> -497 | C25: =-'P&L'!C8 -> -489 | D25: =-Debt!C30 -> 0 | E25: =-Debt!D30 -> 0 | F25: =-Debt!E30 -> 0 | G25: =-Debt!F30 -> 0 | H25: =-Debt!G30 -> 0
A26: Interest expense (transaction debt) | D26: =-Debt!C18 -> -8915.408 | E26: =-Debt!D18 -> -7976.944 | F26: =-Debt!E18 -> -7038.48 | G26: =-Debt!F18 -> -6100.016 | H26: =-Debt!G18 -> -5161.552
A27: PBT | B27: =B23+B25 -> 47973 | C27: =C23+C25+C26 -> 19526 | D27: =D23+D25+D26 -> 20798.327 | E27: =E23+E25+E26 -> 22610.734 | F27: =F23+F25+F26 -> 26876.682 | G27: =G23+G25+G26 -> 31908.432 | H27: =H23+H25+H26 -> 38346.033
A29: Tax (% of base) | B29: 0.2 | C29: 0.2 | D29: =C29 -> 0.2 | E29: =D29 -> 0.2 | F29: =E29 -> 0.2 | G29: =F29 -> 0.2 | H29: =G29 -> 0.2
A30: Tax | B30: =-B29*(B23+B25) -> -9594.6 | C30: =-C29*(C23+C25) -> -3905.2 | D30: =-D29*(D23+D25) -> -5942.7471 | E30: =-E29*(E23+E25) -> -6117.5356 | F30: =-F29*(F23+F25) -> -6783.0324 | G30: =-G29*(G23+G25) -> -7601.6896 | H30: =-H29*(H23+H25) -> -8701.517
A31: Net Income | B31: =B27+B30 -> 38378.4 | C31: =C27+C30 -> 15620.8 | D31: =D27+D30 -> 14855.58 | E31: =E27+E30 -> 16493.199 | F31: =F27+F30 -> 20093.65 | G31: =G27+G30 -> 24306.742 | H31: =H27+H30 -> 29644.516

Sheet Debt
A1: Debt Financing Schedule (thousand PLN)
A3: Transaction debt
A5: Assumptions
A6: Opening balance (2025) | B6: ='Calculations & S&U'!B12 -> 117308
A7: Interest rate (%) | B7: 0.08
A8: Maturity (years) | B8: 5
A9: % of debt as bullet payment | B9: 0.5
A10: Equal principal repayment? (YES/NO) | B10: YES
A12: Year | B12: 2025 | C12: 2026 | D12: 2027 | E12: 2028 | F12: 2029 | G12: 2030
A13: Opening balance | C13: =B16 -> 117308 | D13: =C16 -> 105577.2 | E13: =D16 -> 93846.4 | F13: =E16 -> 82115.6 | G13: =F16 -> 70384.8
A14: Principal repayment (amortized) | C14: =-$B$6*$B$9/$B$8 -> -11730.8 | D14: =-$B$6*$B$9/$B$8 -> -11730.8 | E14: =-$B$6*$B$9/$B$8 -> -11730.8 | F14: =-$B$6*$B$9/$B$8 -> -11730.8 | G14: =-$B$6*$B$9/$B$8 -> -11730.8
A15: Principal repayment (bullet) | G15: =-B6*B9 -> -58654
A16: Closing balance | B16: =B6 -> 117308 | C16: =C13+C14+C15 -> 105577.2 | D16: =D13+D14+D15 -> 93846.4 | E16: =E13+E14+E15 -> 82115.6 | F16: =F13+F14+F15 -> 70384.8 | G16: =G13+G14+G15 -> 0
A18: Interest cost | B18: 0 | C18: =$B$7*AVERAGE(B16:C16) -> 8915.408 | D18: =$B$7*AVERAGE(C16:D16) -> 7976.944 | E18: =$B$7*AVERAGE(D16:E16) -> 7038.48 | F18: =$B$7*AVERAGE(E16:F16) -> 6100.016 | G18: =B7*AVERAGE(G13,G13+G14) -> 5161.552
A20: Other debt
A22: Assumptions
A23: Interest rate (%) | B23: 0.08
A24: `
A25: Year | B25: 2025 | C25: 2026 | D25: 2027 | E25: 2028 | F25: 2029 | G25: 2030
A26: Opening balance | C26: =B28 -> 0
A27: Repayment | C27: =-C26 -> 0
A28: Closing balance | B28: ='Balance sheet'!C28+'Balance sheet'!C31+'Balance sheet'!C32 -> 0 | C28: =C26+C27 -> 0
A30: Interest cost | C30: =B23*C26 -> 0

Sheet WC & CAPEX
A1: Working Capital and CAPEX
A3: Working Capital
A5: Year | B5: 2024 | C5: 2025 | D5: 2026 | E5: 2027 | F5: 2028 | G5: 2029 | H5: 2030
A7: Revenues | B7: ='P&L forecast'!B5 -> 664389 | C7: ='P&L forecast'!C5 -> 653378 | D7: ='P&L forecast'!D5 -> 664214.95 | E7: ='P&L forecast'!E5 -> 677499.25 | F7: ='P&L forecast'!F5 -> 704599.22 | G7: ='P&L forecast'!G5 -> 739829.18 | H7: ='P&L forecast'!H5 -> 791617.22
A9: Inventories | B9: ='Balance sheet'!B4 -> 153890 | C9: ='Balance sheet'!C4 -> 156738 | D9: =D10*D$7 -> 159337.66 | E9: =E10*E$7 -> 162524.42 | F9: =F10*F$7 -> 169025.39 | G9: =G10*G$7 -> 177476.66 | H9: =H10*H$7 -> 189900.03
A10: As % of sales | B10: =B9/B7 -> 0.23162635 | C10: =C9/C7 -> 0.2398887 | D10: =C10 -> 0.2398887 | E10: =D10 -> 0.2398887 | F10: =E10 -> 0.2398887 | G10: =F10 -> 0.2398887 | H10: =G10 -> 0.2398887
A11: Receivables | B11: ='Balance sheet'!B3 -> 86044 | C11: ='Balance sheet'!C3 -> 93382 | D11: =D12*D$7 -> 94930.837 | E11: =E12*E$7 -> 96829.454 | F11: =F12*F$7 -> 100702.63 | G11: =G12*G$7 -> 105737.76 | H11: =H12*H$7 -> 113139.41
A12: As % of sales | B12: =B11/B7 -> 0.12950847 | C12: =C11/C7 -> 0.14292186 | D12: =C12 -> 0.14292186 | E12: =D12 -> 0.14292186 | F12: =E12 -> 0.14292186 | G12: =F12 -> 0.14292186 | H12: =G12 -> 0.14292186
A13: Other current assets | B13: ='Balance sheet'!B5 -> 17962 | C13: ='Balance sheet'!C5 -> 21786 | D13: =D14*D$7 -> 22147.343 | E13: =E14*E$7 -> 22590.29 | F13: =F14*F$7 -> 23493.902 | G13: =G14*G$7 -> 24668.597 | H13: =H14*H$7 -> 26395.399
A14: As % of sales | B14: =B13/B7 -> 0.027035366 | C14: =C13/C7 -> 0.033343639 | D14: =C14 -> 0.033343639 | E14: =D14 -> 0.033343639 | F14: =E14 -> 0.033343639 | G14: =F14 -> 0.033343639 | H14: =G14 -> 0.033343639
A15: Trade payables | B15: ='Balance sheet'!B11 -> 32775 | C15: ='Balance sheet'!C11 -> 34312 | D15: =D16*D$7 -> 34881.1 | E15: =E16*E$7 -> 35578.722 | F15: =F16*F$7 -> 37001.871 | G15: =G16*G$7 -> 38851.964 | H15: =H16*H$7 -> 41571.602
A16: As % of sales | B16: =B15/B7 -> 0.049331039 | C16: =C15/C7 -> 0.052514777 | D16: =C16 -> 0.052514777 | E16: =D16 -> 0.052514777 | F16: =E16 -> 0.052514777 | G16: =F16 -> 0.052514777 | H16: =G16 -> 0.052514777
A17: Other payables | B17: ='Balance sheet'!B12+'Balance sheet'!B15 -> 38695 | C17: ='Balance sheet'!C12+'Balance sheet'!C15 -> 42610 | D17: =D18*D$7 -> 43316.731 | E17: =E18*E$7 -> 44183.066 | F17: =F18*F$7 -> 45950.388 | G17: =G18*G$7 -> 48247.908 | H17: =H18*H$7 -> 51625.261
A18: As % of sales | B18: =B17/B7 -> 0.058241482 | C18: =C17/C7 -> 0.065214929 | D18: =C18 -> 0.065214929 | E18: =D18 -> 0.065214929 | F18: =E18 -> 0.065214929 | G18: =F18 -> 0.065214929 | H18: =G18 -> 0.065214929
A20: Total NWC | B20: =B9+B11+B13-B15-B17 -> 186426 | C20: =C9+C11+C13-C15-C17 -> 194984 | D20: =D9+D11+D13-D15-D17 -> 198218.01 | E20: =E9+E11+E13-E15-E17 -> 202182.37 | F20: =F9+F11+F13-F15-F17 -> 210269.67 | G20: =G9+G11+G13-G15-G17 -> 220783.15 | H20: =H9+H11+H13-H15-H17 -> 236237.97
A21: As % of sales | B21: =B20/B7 -> 0.28059766 | C21: =C20/C7 -> 0.2984245 | D21: =D20/D7 -> 0.2984245 | E21: =E20/E7 -> 0.2984245 | F21: =F20/F7 -> 0.2984245 | G21: =G20/G7 -> 0.2984245 | H21: =H20/H7 -> 0.2984245
A22: Change in NWC | C22: =C20-B20 -> 8558 | D22: =D20-C20 -> 3234.0116 | E22: =E20-D20 -> 3964.3602 | F22: =F20-E20 -> 8087.2949 | G22: =G20-F20 -> 10513.483 | H22: =H20-G20 -> 15454.821
A24: CAPEX
A26: Year | B26: 2024 | C26: 2025 | D26: 2026 | E26: 2027 | F26: 2028 | G26: 2029 | H26: 2030
A28: CAPEX | B28: ='Cash flows'!B7 -> -8223 | C28: ='Cash flows'!C7 -> -7966 | D28: ='Cash flows'!D7 -> -4393.309 | E28: =D28-1000 -> -5393.309 | F28: =E28-1000 -> -6393.309 | G28: =F28-1000 -> -7393.309 | H28: =G28-1000 -> -8393.309

Sheet CF forecast
A1: Income Statement Forecast (thousand PLN)
A3: Income Statement
A4: Item | B4: 2024 | C4: 2025 | D4: 2026B | E4: 2027F | F4: 2028F | G4: 2029F | H4: 2030F
A5: EBITDA | D5: ='P&L forecast'!D15 -> 39131.432 | E5: ='P&L forecast'!E15 -> 40305.375 | F5: ='P&L forecast'!F15 -> 43932.859 | G5: ='P&L forecast'!G15 -> 48326.144 | H5: ='P&L forecast'!H15 -> 54125.282
A6: Change in working capital | D6: =-'WC & CAPEX'!D22 -> -3234.0116 | E6: =-'WC & CAPEX'!E22 -> -3964.3602 | F6: =-'WC & CAPEX'!F22 -> -8087.2949 | G6: =-'WC & CAPEX'!G22 -> -10513.483 | H6: =-'WC & CAPEX'!H22 -> -15454.821
A7: Cash flow from operations (CFO) | D7: =D5+D6 -> 35897.42 | E7: =E5+E6 -> 36341.015 | F7: =F5+F6 -> 35845.564 | G7: =G5+G6 -> 37812.661 | H7: =H5+H6 -> 38670.461
A8: Capital expenditures (CapEx) | D8: ='WC & CAPEX'!D28 -> -4393.309 | E8: ='WC & CAPEX'!E28 -> -5393.309 | F8: ='WC & CAPEX'!F28 -> -6393.309 | G8: ='WC & CAPEX'!G28 -> -7393.309 | H8: ='WC & CAPEX'!H28 -> -8393.309
A9: Cash flow from investing (CFI) | D9: =D8 -> -4393.309 | E9: =E8 -> -5393.309 | F9: =F8 -> -6393.309 | G9: =G8 -> -7393.309 | H9: =H8 -> -8393.309
A10: Changes in debt | D10: =Debt!C14+Debt!C15+Debt!C27 -> -11730.8 | E10: =Debt!D14+Debt!D15+Debt!D27 -> -11730.8 | F10: =Debt!E14+Debt!E15+Debt!E27 -> -11730.8 | G10: =Debt!F14+Debt!F15+Debt!F27 -> -11730.8 | H10: =Debt!G14+Debt!G15+Debt!G27 -> -70384.8
A11: Interest | D11: =-Debt!C18-Debt!C30 -> -8915.408 | E11: =-Debt!D18-Debt!D30 -> -7976.944 | F11: =-Debt!E18-Debt!E30 -> -7038.48 | G11: =-Debt!F18-Debt!F30 -> -6100.016 | H11: =-Debt!G18-Debt!G30 -> -5161.552
A12: Cash flow from financing (CFF) | D12: =D10+D11 -> -20646.208 | E12: =E10+E11 -> -19707.744 | F12: =F10+F11 -> -18769.28 | G12: =G10+G11 -> -17830.816 | H12: =H10+H11 -> -75546.352
A13: Net change in cash | D13: =D7+D9+D12 -> 10857.903 | E13: =E7+E9+E12 -> 11239.962 | F13: =F7+F9+F12 -> 10682.975 | G13: =G7+G9+G12 -> 12588.536 | H13: =H7+H9+H12 -> -45269.2 | K13: `
A14: Cash at the end of period | C14: =-'Balance sheet'!C29 -> 208501 | D14: =C14+D13 -> 219358.9 | E14: =D14+E13 -> 230598.86 | F14: =E14+F13 -> 241281.84 | G14: =F14+G13 -> 253870.38 | H14: =G14+H13 -> 208601.18

Sheet Returns
A1: Returns calculation (thousand $US)
A2: Assumptions
A3: Fund's equity investment (2025) | B3: ='Calculations & S&U'!B24 -> 274989.5
A4: Investment year | B4: 2025 | C4: 31st January
A5: Exit EV/EBITDA multiple | B5: 12
A6: Fund ownership (%) | B6: 0.7
A7: Transaction costs at exit (% of EV) | B7: 0.02
A8: ESOP (% of EQV at exit) | B8: 0.05
A9: Effective Year: | B9: 2024 | C9: 2025 | D9: 2026 | E9: 2027 | F9: 2028 | G9: 2029
B10: FY25(31/01/2024-31/01/2025) | C10: FY26 | D10: FY27 | E10: FY28 | F10: FY29 | G10: FY30
A11: EBITDA (base for valuation) | B11: ='P&L forecast'!C19 -> 29327 | C11: ='P&L forecast'!D19 -> 39131.432 | D11: ='P&L forecast'!E19 -> 40305.375 | E11: ='P&L forecast'!F19 -> 43932.859 | F11: ='P&L forecast'!G19 -> 48326.144 | G11: ='P&L forecast'!H19 -> 54125.282
A12: 100% EV at exit | C12: =C11*$B$5 -> 469577.18 | D12: =D11*$B$5 -> 483664.5 | E12: =E11*$B$5 -> 527194.3 | F12: =F11*$B$5 -> 579913.73 | G12: =G11*$B$5 -> 649503.38
A13: Debt | B13: =Debt!B16+Debt!B28 -> 117308 | C13: =Debt!C16+Debt!C28 -> 105577.2 | D13: =Debt!D16+Debt!D28 -> 93846.4 | E13: =Debt!E16+Debt!E28 -> 82115.6 | F13: =Debt!F16+Debt!F28 -> 70384.8 | G13: =Debt!G16+Debt!G28 -> 0
A14: Cash | B14: ='CF forecast'!C14 -> 208501 | C14: ='CF forecast'!D14 -> 219358.9 | D14: ='CF forecast'!E14 -> 230598.86 | E14: ='CF forecast'!F14 -> 241281.84 | F14: ='CF forecast'!G14 -> 253870.38 | G14: ='CF forecast'!H14 -> 208601.18
A15: Net debt | B15: =B13-B14 -> -91193 | C15: =C13-C14 -> -113781.7 | D15: =D13-D14 -> -136752.46 | E15: =E13-E14 -> -159166.24 | F15: =F13-F14 -> -183485.58 | G15: =G13-G14 -> -208601.18
A16: Net debt/EBITDA | B16: =B15/B11 -> -3.1095236 | C16: =C15/C11 -> -2.9076805 | D16: =D15/D11 -> -3.3929089 | E16: =E15/E11 -> -3.6229429 | F16: =F15/F11 -> -3.796818 | G16: =G15/G11 -> -3.8540432
A17: 100% EQV | C17: =C12-C15 -> 583358.89 | D17: =D12-D15 -> 620416.96 | E17: =E12-E15 -> 686360.54 | F17: =F12-F15 -> 763399.31 | G17: =G12-G15 -> 858104.56
A18: Fund's EQV | C18: =C17*$B$6 -> 408351.22 | D18: =D17*$B$6 -> 434291.87 | E18: =E17*$B$6 -> 480452.38 | F18: =F17*$B$6 -> 534379.52 | G18: =G17*$B$6 -> 600673.19
A20: Exit after 4y: | B20: 45688 | C20: 46053 | D20: 46418 | E20: 46783 | F20: 47149 | G20: 47514
A21: Fund's Investment | B21: =-B3 -> -274989.5
A22: Fund's inflow from sale | G22: =G18 -> 600673.19
A23: ESOP | G23: =-B8*G17*B6 -> -30033.659
A24: Transaction costs at exit | G24: =-B7*G12*B6 -> -9093.0473
A25: Total Fund's proceeds | B25: =SUM(B21:B24) -> -274989.5 | C25: =SUM(C21:C24) -> 0 | D25: =SUM(D21:D24) -> 0 | E25: =SUM(E21:E24) -> 0 | F25: =SUM(F21:F24) -> 0 | G25: =SUM(G21:G24) -> 561546.48
A27: MM | B27: =-G25/B21 -> 2.0420652
A28: IRR | B28: =XIRR(B25:G25,B20:G20) -> 0.15340003
